octo_pipeline_python/backends/patch/__init__.py
octo_pipeline_python/backends/patch/patch_backend.py
octo_pipeline_python/backends/patch/actions/__init__.py
octo_pipeline_python/backends/patch/actions/patch_execute.py
octo_pipeline_python/backends/patch/models/__init__.py
octo_pipeline_python/backends/patch/models/patch_backend_model.py
octo_pipeline_backend_patch_python-1.3.2.dist-info/LICENSE.txt
octo_pipeline_backend_patch_python-1.3.2.dist-info/METADATA
octo_pipeline_backend_patch_python-1.3.2.dist-info/README.md
octo_pipeline_backend_patch_python-1.3.2.dist-info/WHEEL
octo_pipeline_backend_patch_python-1.3.2.dist-info/top_level.txt
octo_pipeline_backend_patch_python-1.3.2.dist-info/RECORD
